pipeline_telemetry/__init__.py
pipeline_telemetry/decorator.py
pipeline_telemetry/helper.py
pipeline_telemetry/main.py
pipeline_telemetry/mixin.py
pipeline_telemetry/aggregator/__init__.py
pipeline_telemetry/aggregator/aggregator.py
pipeline_telemetry/aggregator/helper.py
pipeline_telemetry/aggregator/mongo_aggregator.py
pipeline_telemetry/data_classes/__init__.py
pipeline_telemetry/data_classes/telemetry_models.py
pipeline_telemetry/settings/__init__.py
pipeline_telemetry/settings/data_class.py
pipeline_telemetry/settings/date_ranges.py
pipeline_telemetry/settings/exceptions.py
pipeline_telemetry/settings/process_type.py
pipeline_telemetry/settings/settings.py
pipeline_telemetry/settings/telemetry_errors.py
pipeline_telemetry/storage/__init__.py
pipeline_telemetry/storage/generic.py
pipeline_telemetry/storage/memory.py
pipeline_telemetry/storage/mongo.py
pipeline_telemetry/storage/mongo_bunnet.py
pipeline_telemetry/storage/mongo_connection.py
pipeline_telemetry/validators/__init__.py
pipeline_telemetry/validators/abstract_validator_instruction.py
pipeline_telemetry/validators/dict_validator.py
pipeline_telemetry/validators/entries_have_key.py
pipeline_telemetry/validators/has_key.py
pipeline_telemetry/validators/validate_entries.py
pipeline_telemetry-1.1.0.dist-info/LICENSE
pipeline_telemetry-1.1.0.dist-info/METADATA
pipeline_telemetry-1.1.0.dist-info/WHEEL
pipeline_telemetry-1.1.0.dist-info/top_level.txt
pipeline_telemetry-1.1.0.dist-info/RECORD
