Metadata-Version: 2.1
Name: pipeline-telemetry
Version: 1.1.0
Summary: Measure your data pipelines with easy to use telemetry logic
Home-page: https://github.com/MaartendeRuyter/pipeline-telemetry
Author: Maarten de Ruyter
Author-email: "Maarten de Ruyter" <maarten@geodatagarden.com>
License: GNU
Classifier: License :: OSI Approved :: GNU Lesser General Public License v3 or later (LGPLv3+)
Classifier: Intended Audience :: Developers
Classifier: Programming Language :: Python
Classifier: Programming Language :: Python :: 3
Classifier: Programming Language :: Python :: 3 :: Only
Classifier: Programming Language :: Python :: 3.10
Classifier: Programming Language :: Python :: 3.11
Classifier: Programming Language :: Python :: 3.12
License-File: LICENSE
Requires-Dist: error-manager
Requires-Dist: mongoengine
Requires-Dist: jmespath
Requires-Dist: bunnet
